{"__type__":"cc.TextAsset","_name":"19","text":"{\"idioms\":[{\"id\":46,\"grids\":[{\"id\":13,\"space\":true},{\"id\":22,\"space\":true},{\"id\":31,\"space\":false},{\"id\":40,\"space\":false}]},{\"id\":5188,\"grids\":[{\"id\":31,\"space\":false},{\"id\":32,\"space\":true},{\"id\":33,\"space\":false},{\"id\":34,\"space\":true}]},{\"id\":312,\"grids\":[{\"id\":34,\"space\":true},{\"id\":43,\"space\":false},{\"id\":52,\"space\":false},{\"id\":61,\"space\":true}]},{\"id\":93,\"grids\":[{\"id\":59,\"space\":false},{\"id\":60,\"space\":true},{\"id\":61,\"space\":true},{\"id\":62,\"space\":false}]},{\"id\":1948,\"grids\":[{\"id\":19,\"space\":false},{\"id\":20,\"space\":false},{\"id\":21,\"space\":true},{\"id\":22,\"space\":true}]}]}"}